webscrapper/__init__.py
webscrapper/client.py
webscrapper/tests.py
webscrapper-0.1.0.dist-info/LICENSE
webscrapper-0.1.0.dist-info/METADATA
webscrapper-0.1.0.dist-info/WHEEL
webscrapper-0.1.0.dist-info/top_level.txt
webscrapper-0.1.0.dist-info/RECORD
