Metadata-Version: 2.1
Name: webscrapper
Version: 0.1.0
Summary: Simple client for Web scrapper API https://scrapper.scurra.space/
Home-page: https://github.com/pi11/webscrapper-client-python
Author: webii
Author-email: webii@pm.me
Classifier: Programming Language :: Python :: 3
Classifier: Operating System :: OS Independent
Requires-Python: >=3.6
License-File: LICENSE
